{
  "nome": "Gabriel Jappe",
  "idade": "15",
  "sexo": "masc",
  "peso": "56",
  "altura": "165",
  "atividadeRegular": "nao",
  "atividadeQuais": "",
  "sono": "5-8 horas",
  "doenca": "nao",
  "qualDoenca": "",
  "deficiencia": "nao",
  "qualDeficiencia": "",
  "cirurgia": "nao",
  "qualCirurgia": "",
  "medicamento": "nao",
  "qualCirur": "",
  "alcool": "nao",
  "fumo": "nao",
  "atividadeNovaFrequencia": "2-3 dias",
  "atividadeNovaPeriodo": "tarde",
  "atividadeNovaTempo": "30min-1hora",
  "atividadeNovaIntensidade": "intermediaria",
  "infoExtra": ""
}